design/Control_Unit.v
module Control_Uint(
    input        clk,
    input        rst,
    input  [6:0] ALUSEL,

    output reg  PC_en,
    output reg  ID_en,
    output reg  EX_en,
    output reg  MEM_en,
    output reg  WB_en,

    output reg          Jump_en,
    output reg          imm_en,
    output reg          EXPC_en,
    output reg          L_or_S,
    output reg  [1:0]   WB_Ctrl
);

parameter   PC  = 3'b000;
parameter   ID  = 3'b001;
parameter   EX  = 3'b010;
parameter   MEM = 3'b011;
parameter   WB  = 3'b100;

parameter   Jump = 3'b100;

reg [2:0]   st_cur;
reg [2:0]   st_next;

always @(posedge clk or posedge rst or negedge rst)
begin
    if(!rst)
        begin
            PC_en   <= 0;
            ID_en   <= 0;
            EX_en   <= 0;
            MEM_en  <= 0;
            WB_en   <= 0;
            Jump_en <= 0;
            imm_en  <= 0;
            L_or_S  <= 0;
            WB_Ctrl <= 0;

            st_cur  <= PC;
        end
    else
        begin
            st_cur  <=  st_next;
        end
end

always @(*) begin
    case (st_cur)
        PC: 
            begin
                Jump_en = ALUSEL[6];
                PC_en   = 1;
                ID_en   = 0;
                EX_en   = 0;
                MEM_en  = 0;
                WB_en   = 0;
                st_next = ID;
            end
        ID:
            begin
                PC_en   = 0;
                ID_en   = 1;
                EX_en   = 0;
                MEM_en  = 0;
                WB_en   = 0;                
                st_next = EX;
            end
        EX:
            begin
                imm_en  = ALUSEL[5];
                EXPC_en = ALUSEL[2:1] == 2'b01 ? 1 : 0;
                PC_en   = 0;
                ID_en   = 0;
                EX_en   = 1;
                MEM_en  = 0;
                WB_en   = 0; 
                st_next = ALUSEL[0] ? (ALUSEL[3] ? MEM : WB) : PC;
            end
        MEM:
            begin
                L_or_S  = ALUSEL[4];
                PC_en   = 0;
                ID_en   = 0;
                EX_en   = 0;
                MEM_en  = 1;
                WB_en   = 0; 
                st_next = ALUSEL[4] ? PC : WB;
            end
        WB:
            begin
                WB_Ctrl = ALUSEL[2:1];
                PC_en   = 0;
                ID_en   = 0;
                EX_en   = 0;
                MEM_en  = 0;
                WB_en   = 1; 
                st_next = PC;
            end
        default: 
            begin
                PC_en   <= 1;
                ID_en   <= 1;
                EX_en   <= 1;
                MEM_en  <= 1;
                WB_en   <= 1;
                Jump_en <= 1;
                imm_en  <= 1;
                L_or_S  <= 1;
                WB_Ctrl <= 1;
                st_next = PC;
            end
    endcase
end

endmodule

sim/cu_tb.v
`timescale 1ns / 1ps
module cu_tb();
    reg clk;
    reg rst;
    reg [6:0] ALUSEL;

    wire PC_en;
    wire ID_en;
    wire EX_en;
    wire MEM_en;
    wire WB_en;

    wire Jump_en;
    wire imm_en;
    wire EXPC_en;
    wire L_or_S;
    wire [1:0] WB_Ctrl;

    Control_Uint CU(
        .clk(clk),
        .rst(rst),
        .ALUSEL(ALUSEL),

        .PC_en(PC_en),
        .ID_en(ID_en),
        .EX_en(EX_en),
        .MEM_en(MEM_en),
        .WB_en(WB_en),

        .Jump_en(Jump_en),
        .imm_en(imm_en),
        .EXPC_en(EXPC_en),
        .L_or_S(L_or_S),
        .WB_Ctrl(WB_Ctrl)
    );

    initial begin
        
        rst = 0;
        ALUSEL = 7'b0000000;

        #5 rst = 1; // Release reset
        #5 ALUSEL = 7'b0000101; // Set ALUSEL to a new value
        #5 ALUSEL = 7'b0100101; // Change ALUSEL again
        #5 rst = 0; // Assert reset again
        #5 rst = 1; // Release reset again

        #1000 $finish; // End simulation
    end
    initial begin
        clk = 0;
        forever begin
        #10
        clk = ~clk;
        end
    end
    initial begin
        $dumpfile("wave.vcd");
        $dumpvars(0, cu_tb);
    end
endmodule

sim/wave.vcd
$date
	Wed Apr 16 21:31:09 2025
$end
$version
	Icarus Verilog
$end
$timescale
	1ps
$end
$scope module cu_tb $end
$var wire 1 ! imm_en $end
$var wire 1 " WB_en $end
$var wire 2 # WB_Ctrl [1:0] $end
$var wire 1 $ PC_en $end
$var wire 1 % MEM_en $end
$var wire 1 & L_or_S $end
$var wire 1 ' Jump_en $end
$var wire 1 ( ID_en $end
$var wire 1 ) EX_en $end
$var wire 1 * EXPC_en $end
$var reg 7 + ALUSEL [6:0] $end
$var reg 1 , clk $end
$var reg 1 - rst $end
$scope module CU $end
$var wire 7 . ALUSEL [6:0] $end
$var wire 1 , clk $end
$var wire 1 - rst $end
$var parameter 3 / EX $end
$var parameter 3 0 ID $end
$var parameter 3 1 Jump $end
$var parameter 3 2 MEM $end
$var parameter 3 3 PC $end
$var parameter 3 4 WB $end
$var reg 1 * EXPC_en $end
$var reg 1 ) EX_en $end
$var reg 1 ( ID_en $end
$var reg 1 ' Jump_en $end
$var reg 1 & L_or_S $end
$var reg 1 % MEM_en $end
$var reg 1 $ PC_en $end
$var reg 2 5 WB_Ctrl [1:0] $end
$var reg 1 " WB_en $end
$var reg 1 ! imm_en $end
$var reg 3 6 st_cur [2:0] $end
$var reg 3 7 st_next [2:0] $end
$upscope $end
$upscope $end
$enddefinitions $end
$comment Show the parameter values. $end
$dumpall
b100 4
b0 3
b11 2
b100 1
b1 0
b10 /
$end
#0
$dumpvars
b1 7
b0 6
b0 5
b0 .
0-
0,
b0 +
x*
0)
0(
0'
0&
0%
1$
b0 #
0"
0!
$end
#5000
b10 7
1(
0$
b1 6
1-
#10000
b100 7
1)
0(
0*
b10 6
b101 +
b101 .
1,
#15000
1!
b100101 +
b100101 .
#20000
b1 7
1$
b0 6
0!
0)
0-
0,
#25000
b10 7
1(
0$
b1 6
1-
#30000
b100 7
1)
0(
1!
b10 6
1,
#40000
0,
#50000
b0 7
1"
0)
b10 #
b10 5
b100 6
1,
#60000
0,
#70000
b1 7
0"
1$
b0 6
1,
#80000
0,
#90000
b10 7
1(
0$
b1 6
1,
#100000
0,
#110000
b100 7
1)
0(
b10 6
1,
#120000
0,
#130000
b0 7
1"
0)
b100 6
1,
#140000
0,
#150000
b1 7
0"
1$
b0 6
1,
#160000
0,
#170000
b10 7
1(
0$
b1 6
1,
#180000
0,
#190000
b100 7
1)
0(
b10 6
1,
#200000
0,
#210000
b0 7
1"
0)
b100 6
1,
#220000
0,
#230000
b1 7
0"
1$
b0 6
1,
#240000
0,
#250000
b10 7
1(
0$
b1 6
1,
#260000
0,
#270000
b100 7
1)
0(
b10 6
1,
#280000
0,
#290000
b0 7
1"
0)
b100 6
1,
#300000
0,
#310000
b1 7
0"
1$
b0 6
1,
#320000
0,
#330000
b10 7
1(
0$
b1 6
1,
#340000
0,
#350000
b100 7
1)
0(
b10 6
1,
#360000
0,
#370000
b0 7
1"
0)
b100 6
1,
#380000
0,
#390000
b1 7
0"
1$
b0 6
1,
#400000
0,
#410000
b10 7
1(
0$
b1 6
1,
#420000
0,
#430000
b100 7
1)
0(
b10 6
1,
#440000
0,
#450000
b0 7
1"
0)
b100 6
1,
#460000
0,
#470000
b1 7
0"
1$
b0 6
1,
#480000
0,
#490000
b10 7
1(
0$
b1 6
1,
#500000
0,
#510000
b100 7
1)
0(
b10 6
1,
#520000
0,
#530000
b0 7
1"
0)
b100 6
1,
#540000
0,
#550000
b1 7
0"
1$
b0 6
1,
#560000
0,
#570000
b10 7
1(
0$
b1 6
1,
#580000
0,
#590000
b100 7
1)
0(
b10 6
1,
#600000
0,
#610000
b0 7
1"
0)
b100 6
1,
#620000
0,
#630000
b1 7
0"
1$
b0 6
1,
#640000
0,
#650000
b10 7
1(
0$
b1 6
1,
#660000
0,
#670000
b100 7
1)
0(
b10 6
1,
#680000
0,
#690000
b0 7
1"
0)
b100 6
1,
#700000
0,
#710000
b1 7
0"
1$
b0 6
1,
#720000
0,
#730000
b10 7
1(
0$
b1 6
1,
#740000
0,
#750000
b100 7
1)
0(
b10 6
1,
#760000
0,
#770000
b0 7
1"
0)
b100 6
1,
#780000
0,
#790000
b1 7
0"
1$
b0 6
1,
#800000
0,
#810000
b10 7
1(
0$
b1 6
1,
#820000
0,
#830000
b100 7
1)
0(
b10 6
1,
#840000
0,
#850000
b0 7
1"
0)
b100 6
1,
#860000
0,
#870000
b1 7
0"
1$
b0 6
1,
#880000
0,
#890000
b10 7
1(
0$
b1 6
1,
#900000
0,
#910000
b100 7
1)
0(
b10 6
1,
#920000
0,
#930000
b0 7
1"
0)
b100 6
1,
#940000
0,
#950000
b1 7
0"
1$
b0 6
1,
#960000
0,
#970000
b10 7
1(
0$
b1 6
1,
#980000
0,
#990000
b100 7
1)
0(
b10 6
1,
#1000000
0,
#1010000
b0 7
1"
0)
b100 6
1,
