MIPS32CPU/head/defines.v
`ifndef DEFINES_V
`define DEFINES_V
`endif


//-------------------     Global     ------------------------
`define RstEnable       1'b1
`define RstDisable      1'b0
`define ZeroWord        32'h00000000
`define WriteEnable     1'b1
`define WriteDisable    1'b0
`define ReadEnable      1'b1
`define ReadDisable     1'b0
`define AluOpBus        7:0
`define AluSelBus       2:0
`define InstValid       1'b0
`define InstInvalid     1'b1
`define True_v          1'b1
`define False_v         1'b0
`define ChipEnable      1'b1
`define ChipDisable     1'b0



//-------------------     Instruction  -----------------------
`define EXE_ORI         6'b001101
`define EXE_NOP         6'b000000


//AluOp
`define EXE_OR_OP       8'b00100101
`define EXE_NOP_OP      8'b00000000



//AluSel
`define EXE_RES_LOGIC   3'b001

`define EXE_RES_NOP     3'b000



//-------------------    InstRom     -------------------------
`define InstAddrBus     31:0
`define InstBus         31:0
`define InstMemNum      131071
`define InstMemNumLog2  17



//-------------------    RegFile     -------------------------
`define RegAddrBus      4:0
`define RegBus          31:0
`define RegWidth        32
`define DoubleRegWidth  64
`define DoubleRegBus    63:0
`define RegNum          32
`define RegNumLog2      5
`define NopRegAddr      5'b00000

MIPS32CPU/source/design/pc_reg.v
`include "defines.v"
module pc_reg (
    input   wire    rst,
    input   wire    clk,
    output  reg[`InstAddrBus]     pc,
    output  reg     ce
);

    always @ (posedge clk) begin
        if (rst == `RstEnable) begin
            ce <= `ChipDisable;
        end else begin
            ce <= `ChipEnable;
        end
    end

    always @ (posedge clk) begin
        if (ce == `ChipDisable) begin
            pc <= `ZeroWord;
        end else begin
            pc <= pc + 4'h4;
        end
    end

endmodule

MIPS32CPU/source/sim/tb_pc_reg.v
`timescale 1ns/1ns
module tb_pc_reg;
    reg clk, rst;
    wire[`InstAddrBus] pc;
    wire ce;

    initial begin
      clk = 1'b0;
      forever #10 clk = ~clk;
    end

    initial begin
      rst = `RstEnable;
      #195 rst = `RstDisable;
      #1000 $stop;
    end

    initial begin
      $monitor ("InstAddr = %h\tce = %b" ,pc ,ce );
    end

    initial begin
      $dumpfile ("./build/wave.vcd");
      $dumpvars (0, tb_pc_reg);
    end

    pc_reg inst_pc_reg(
      .clk(clk),
      .rst(rst),
      .pc(pc),
      .ce(ce)
    );

endmodule

MIPS32CPU/build/wave.vcd
$date
	Fri Jan 17 19:36:10 2025
$end
$version
	Icarus Verilog
$end
$timescale
	1ns
$end
$scope module tb_pc_reg $end
$var wire 32 ! pc [31:0] $end
$var wire 1 " ce $end
$var reg 1 # clk $end
$var reg 1 $ rst $end
$scope module inst_pc_reg $end
$var wire 1 # clk $end
$var wire 1 $ rst $end
$var reg 1 " ce $end
$var reg 32 % pc [31:0] $end
$upscope $end
$upscope $end
$enddefinitions $end
$comment Show the parameter values. $end
$dumpall
$end
#0
$dumpvars
bx %
1$
0#
x"
bx !
$end
#10
0"
1#
#20
0#
#30
b0 !
b0 %
1#
#40
0#
#50
1#
#60
0#
#70
1#
#80
0#
#90
1#
#100
0#
#110
1#
#120
0#
#130
1#
#140
0#
#150
1#
#160
0#
#170
1#
#180
0#
#190
1#
#195
0$
#200
0#
#210
1"
1#
#220
0#
#230
b100 !
b100 %
1#
#240
0#
#250
b1000 !
b1000 %
1#
#260
0#
#270
b1100 !
b1100 %
1#
#280
0#
#290
b10000 !
b10000 %
1#
#300
0#
#310
b10100 !
b10100 %
1#
#320
0#
#330
b11000 !
b11000 %
1#
#340
0#
#350
b11100 !
b11100 %
1#
#360
0#
#370
b100000 !
b100000 %
1#
#380
0#
#390
b100100 !
b100100 %
1#
#400
0#
#410
b101000 !
b101000 %
1#
#420
0#
#430
b101100 !
b101100 %
1#
#440
0#
#450
b110000 !
b110000 %
1#
#460
0#
#470
b110100 !
b110100 %
1#
#480
0#
#490
b111000 !
b111000 %
1#
#500
0#
#510
b111100 !
b111100 %
1#
#520
0#
#530
b1000000 !
b1000000 %
1#
#540
0#
#550
b1000100 !
b1000100 %
1#
#560
0#
#570
b1001000 !
b1001000 %
1#
#580
0#
#590
b1001100 !
b1001100 %
1#
#600
0#
#610
b1010000 !
b1010000 %
1#
#620
0#
#630
b1010100 !
b1010100 %
1#
#640
0#
#650
b1011000 !
b1011000 %
1#
#660
0#
#670
b1011100 !
b1011100 %
1#
#680
0#
#690
b1100000 !
b1100000 %
1#
#700
0#
#710
b1100100 !
b1100100 %
1#
#720
0#
#730
b1101000 !
b1101000 %
1#
#740
0#
#750
b1101100 !
b1101100 %
1#
#760
0#
#770
b1110000 !
b1110000 %
1#
#780
0#
#790
b1110100 !
b1110100 %
1#
#800
0#
#810
b1111000 !
b1111000 %
1#
#820
0#
#830
b1111100 !
b1111100 %
1#
#840
0#
#850
b10000000 !
b10000000 %
1#
#860
0#
#870
b10000100 !
b10000100 %
1#
#880
0#
#890
b10001000 !
b10001000 %
1#
#900
0#
#910
b10001100 !
b10001100 %
1#
#920
0#
#930
b10010000 !
b10010000 %
1#
#940
0#
#950
b10010100 !
b10010100 %
1#
#960
0#
#970
b10011000 !
b10011000 %
1#
#980
0#
#990
b10011100 !
b10011100 %
1#
#1000
0#
#1010
b10100000 !
b10100000 %
1#
#1020
0#
#1030
b10100100 !
b10100100 %
1#
#1040
0#
#1050
b10101000 !
b10101000 %
1#
#1060
0#
#1070
b10101100 !
b10101100 %
1#
#1080
0#
#1090
b10110000 !
b10110000 %
1#
#1100
0#
#1110
b10110100 !
b10110100 %
1#
#1120
0#
#1130
b10111000 !
b10111000 %
1#
#1140
0#
#1150
b10111100 !
b10111100 %
1#
#1160
0#
#1170
b11000000 !
b11000000 %
1#
#1180
0#
#1190
b11000100 !
b11000100 %
1#
